README.md
setup.py
./colosseum_exporter_launcher/launcher.py
colosseum_exporter_launcher.egg-info/PKG-INFO
colosseum_exporter_launcher.egg-info/SOURCES.txt
colosseum_exporter_launcher.egg-info/dependency_links.txt
colosseum_exporter_launcher.egg-info/requires.txt
colosseum_exporter_launcher.egg-info/top_level.txt