Metadata-Version: 1.2
Name: colosseum-exporter-launcher
Version: 0.2.5
Summary: launches exporters for colosseum via docker container
Home-page: https://github.com/42maru/colosseum_exporter_launcher
Author: Marc
Author-email: marc@42maru.com
License: MIT
Download-URL: https://github.com/42maru/colosseum_exporter_launcher/archive/master.zip
Keywords: colosseum,prometheus,exporter
Platform: UNKNOWN
Requires-Python: >=3.5
